README.md
setup.py
pigmento/__init__.py
pigmento/pigmento.py
pigmento/time_prefix.py
pigmento.egg-info/PKG-INFO
pigmento.egg-info/SOURCES.txt
pigmento.egg-info/dependency_links.txt
pigmento.egg-info/requires.txt
pigmento.egg-info/top_level.txt
pigmento/plugins/__init__.py
pigmento/plugins/base_plugin.py
pigmento/plugins/dynamic_color_plugin.py
pigmento/plugins/log_plugin.py
pigmento/utils/__init__.py
pigmento/utils/bracket.py
pigmento/utils/color.py
pigmento/utils/prefix.py
test_folder/__init__.py
test_folder/a.py
test_folder/b.py